gibbs/__init__.py
gibbs/hub.py
gibbs/worker.py
gibbs-0.2.0.dist-info/LICENSE
gibbs-0.2.0.dist-info/METADATA
gibbs-0.2.0.dist-info/WHEEL
gibbs-0.2.0.dist-info/top_level.txt
gibbs-0.2.0.dist-info/RECORD
